RTL/digital_pll_controller.v
// SPDX-FileCopyrightText: 2020 Efabless Corporation
//
// Licensed under the Apache License, Version 2.0 (the "License");
// you may not use this file except in compliance with the License.
// You may obtain a copy of the License at
//
//      http://www.apache.org/licenses/LICENSE-2.0
//
// Unless required by applicable law or agreed to in writing, software
// distributed under the License is distributed on an "AS IS" BASIS,
// WITHOUT WARRANTIES OR CONDITIONS OF ANY KIND, either express or implied.
// See the License for the specific language governing permissions and
// limitations under the License.
// SPDX-License-Identifier: Apache-2.0

`default_nettype none
// (True) digital PLL
//
// Output goes to a trimmable ring oscillator (see documentation).
// Ring oscillator should be trimmable to above and below maximum
// ranges of the input.
//
// Input "osc" comes from a fixed clock source (e.g., crystal oscillator
// output).
//
// Input "div" is the target number of clock cycles per oscillator cycle.
// e.g., if div == 8 then this is an 8X PLL.
//
// Clock "clock" is the PLL output being trimmed.
// (NOTE:  To be done:  Pass-through enable)
//
// Algorithm:
//
// 1) Trim is done by thermometer code.  Reset to the highest value
//    in case the fastest rate clock is too fast for the logic.
//
// 2) Count the number of contiguous 1s and 0s in "osc"
//    periods of the master clock.  If the count maxes out, it does
//    not roll over.
//
// 3) Add the two counts together.
//
// 4) If the sum is less than div, then the clock is too slow, so
//    decrease the trim code.  If the sum is greater than div, the
//    clock is too fast, so increase the trim code.  If the sum
//    is equal to div, the the trim code does not change.
//

module pll_controller(reset, clock, osc, div, trim);
    input reset;
    input clock;
    input osc;
    input [4:0] div;
    output [25:0] trim;		// Use ring_osc2x13, with 26 trim bits

    wire [25:0] trim;
    reg [2:0] oscbuf;
    reg [2:0] prep;

    reg [4:0] count0;
    reg [4:0] count1;
    reg [6:0] tval;	// Includes 2 bits fractional
    wire [4:0] tint;	// Integer part of the above

    wire [5:0] sum;

    assign sum = count0 + count1;
 
    // Integer to thermometer code (maybe there's an algorithmic way?)
    assign tint = tval[6:2];
                                     // |<--second-->|<-- first-->|
    assign trim = (tint == 5'd0)  ? 26'b0000000000000_0000000000000 :
          (tint == 5'd1)  ? 26'b0000000000000_0000000000001 :
          (tint == 5'd2)  ? 26'b0000000000000_0000001000001 :
          (tint == 5'd3)  ? 26'b0000000000000_0010001000001 :
          (tint == 5'd4)  ? 26'b0000000000000_0010001001001 :
          (tint == 5'd5)  ? 26'b0000000000000_0010101001001 :
          (tint == 5'd6)  ? 26'b0000000000000_1010101001001 :
          (tint == 5'd7)  ? 26'b0000000000000_1010101101001 :
          (tint == 5'd8)  ? 26'b0000000000000_1010101101101 :
          (tint == 5'd9)  ? 26'b0000000000000_1011101101101 :
          (tint == 5'd10) ? 26'b0000000000000_1011101111101 :
          (tint == 5'd11) ? 26'b0000000000000_1111101111101 :
          (tint == 5'd12) ? 26'b0000000000000_1111101111111 :
          (tint == 5'd13) ? 26'b0000000000000_1111111111111 :
          (tint == 5'd14) ? 26'b0000000000001_1111111111111 :
          (tint == 5'd15) ? 26'b0000001000001_1111111111111 :
          (tint == 5'd16) ? 26'b0010001000001_1111111111111 :
          (tint == 5'd17) ? 26'b0010001001001_1111111111111 :
          (tint == 5'd18) ? 26'b0010101001001_1111111111111 :
          (tint == 5'd19) ? 26'b1010101001001_1111111111111 :
          (tint == 5'd20) ? 26'b1010101101001_1111111111111 :
          (tint == 5'd21) ? 26'b1010101101101_1111111111111 :
          (tint == 5'd22) ? 26'b1011101101101_1111111111111 :
          (tint == 5'd23) ? 26'b1011101111101_1111111111111 :
          (tint == 5'd24) ? 26'b1111101111101_1111111111111 :
          (tint == 5'd25) ? 26'b1111101111111_1111111111111 :
                    26'b1111111111111_1111111111111;
   
    always @(posedge clock or posedge reset) begin
    if (reset == 1'b1) begin
        tval <= 7'd0;	// Note:  trim[0] must be zero for startup to work.
        oscbuf <= 3'd0;
        prep <= 3'd0;
        count0 <= 5'd0;
        count1 <= 5'd0;

    end else begin
        oscbuf <= {oscbuf[1:0], osc};

        if (oscbuf[2] != oscbuf[1]) begin
        count1 <= count0;
        count0 <= 5'b00001;
        prep <= {prep[1:0], 1'b1};

        if (prep == 3'b111) begin
            if (sum > div) begin
		if (tval < 127) begin
            	    tval <= tval + 1;
		end
            end else if (sum < div) begin
		if (tval > 0) begin
            	    tval <= tval - 1;
		end
            end
        end
        end else begin
        if (count0 != 5'b11111) begin
                count0 <= count0 + 1;
        end
        end
    end
    end

endmodule	// digital_pll_controller
`default_nettype wire

tb/tb_pll_controller_reset.v
`timescale 1ns/1ps

module tb_pll_controller_reset;
	reg reset;
	reg clock;
	reg Fref;
	reg [4:0] div;
	
	wire [25:0] trim;

	pll_controller uut(
	.reset(reset),
	.clock(clock),
	.osc(Fref),
	.div(div),
	.trim(trim)
	);
	
	initial begin
		
	$dumpfile("pll_controller_reset.vcd");
	$dumpvars(0,tb_pll_controller_reset);
	
	reset = 1'b1;
	div = 5'd8;
	Fref =0;
	clock=0;
	#50;
	reset =1'b0;
	
	#300;
	reset =1'b1;
	#200
        $finish;
	
	end
	
	always #5 clock = ~clock;
        always #40 Fref = ~Fref;	
        
endmodule

waves/waves_pll_controller_reset.vcd
$date
	Sun Jul  6 16:20:01 2025
$end
$version
	Icarus Verilog
$end
$timescale
	1ps
$end
$scope module tb_pll_controller_reset $end
$var wire 26 ! trim [25:0] $end
$var reg 1 " Fref $end
$var reg 1 # clock $end
$var reg 5 $ div [4:0] $end
$var reg 1 % reset $end
$scope module uut $end
$var wire 1 # clock $end
$var wire 5 & div [4:0] $end
$var wire 1 " osc $end
$var wire 1 % reset $end
$var wire 26 ' trim [25:0] $end
$var wire 5 ( tint [4:0] $end
$var wire 6 ) sum [5:0] $end
$var reg 5 * count0 [4:0] $end
$var reg 5 + count1 [4:0] $end
$var reg 3 , oscbuf [2:0] $end
$var reg 3 - prep [2:0] $end
$var reg 7 . tval [6:0] $end
$upscope $end
$upscope $end
$enddefinitions $end
#0
$dumpvars
b0 .
b0 -
b0 ,
b0 +
b0 *
b0 )
b0 (
b0 '
b1000 &
1%
b1000 $
0#
0"
b0 !
$end
#5000
1#
#10000
0#
#15000
1#
#20000
0#
#25000
1#
#30000
0#
#35000
1#
#40000
0#
1"
#45000
1#
#50000
0#
0%
#55000
b1 )
b1 *
b1 ,
1#
#60000
0#
#65000
b10 )
b10 *
b11 ,
1#
#70000
0#
#75000
b1 -
b1 *
b11 )
b10 +
b111 ,
1#
#80000
0#
0"
#85000
b100 )
b10 *
b110 ,
1#
#90000
0#
#95000
b101 )
b11 *
b100 ,
1#
#100000
0#
#105000
b11 -
b1 *
b100 )
b11 +
b0 ,
1#
#110000
0#
#115000
b101 )
b10 *
1#
#120000
0#
1"
#125000
b110 )
b11 *
b1 ,
1#
#130000
0#
#135000
b111 )
b100 *
b11 ,
1#
#140000
0#
#145000
b111 -
b1 *
b101 )
b100 +
b111 ,
1#
#150000
0#
#155000
b110 )
b10 *
1#
#160000
0#
0"
#165000
b111 )
b11 *
b110 ,
1#
#170000
0#
#175000
b1000 )
b100 *
b100 ,
1#
#180000
0#
#185000
b101 )
b1 *
b0 ,
1#
#190000
0#
#195000
b110 )
b10 *
1#
#200000
0#
1"
#205000
b111 )
b11 *
b1 ,
1#
#210000
0#
#215000
b1000 )
b100 *
b11 ,
1#
#220000
0#
#225000
b101 )
b1 *
b111 ,
1#
#230000
0#
#235000
b110 )
b10 *
1#
#240000
0#
0"
#245000
b111 )
b11 *
b110 ,
1#
#250000
0#
#255000
b1000 )
b100 *
b100 ,
1#
#260000
0#
#265000
b101 )
b1 *
b0 ,
1#
#270000
0#
#275000
b110 )
b10 *
1#
#280000
0#
1"
#285000
b111 )
b11 *
b1 ,
1#
#290000
0#
#295000
b1000 )
b100 *
b11 ,
1#
#300000
0#
#305000
b101 )
b1 *
b111 ,
1#
#310000
0#
#315000
b110 )
b10 *
1#
#320000
0#
0"
#325000
b111 )
b11 *
b110 ,
1#
#330000
0#
#335000
b1000 )
b100 *
b100 ,
1#
#340000
0#
#345000
b101 )
b1 *
b0 ,
1#
#350000
b0 +
b0 )
b0 *
b0 -
0#
1%
#355000
1#
#360000
0#
1"
#365000
1#
#370000
0#
#375000
1#
#380000
0#
#385000
1#
#390000
0#
#395000
1#
#400000
0#
0"
#405000
1#
#410000
0#
#415000
1#
#420000
0#
#425000
1#
#430000
0#
#435000
1#
#440000
0#
1"
#445000
1#
#450000
0#
#455000
1#
#460000
0#
#465000
1#
#470000
0#
#475000
1#
#480000
0#
0"
#485000
1#
#490000
0#
#495000
1#
#500000
0#
#505000
1#
#510000
0#
#515000
1#
#520000
0#
1"
