RTL/digital_pll_controller.v
// SPDX-FileCopyrightText: 2020 Efabless Corporation
//
// Licensed under the Apache License, Version 2.0 (the "License");
// you may not use this file except in compliance with the License.
// You may obtain a copy of the License at
//
//      http://www.apache.org/licenses/LICENSE-2.0
//
// Unless required by applicable law or agreed to in writing, software
// distributed under the License is distributed on an "AS IS" BASIS,
// WITHOUT WARRANTIES OR CONDITIONS OF ANY KIND, either express or implied.
// See the License for the specific language governing permissions and
// limitations under the License.
// SPDX-License-Identifier: Apache-2.0

`default_nettype none
// (True) digital PLL
//
// Output goes to a trimmable ring oscillator (see documentation).
// Ring oscillator should be trimmable to above and below maximum
// ranges of the input.
//
// Input "osc" comes from a fixed clock source (e.g., crystal oscillator
// output).
//
// Input "div" is the target number of clock cycles per oscillator cycle.
// e.g., if div == 8 then this is an 8X PLL.
//
// Clock "clock" is the PLL output being trimmed.
// (NOTE:  To be done:  Pass-through enable)
//
// Algorithm:
//
// 1) Trim is done by thermometer code.  Reset to the highest value
//    in case the fastest rate clock is too fast for the logic.
//
// 2) Count the number of contiguous 1s and 0s in "osc"
//    periods of the master clock.  If the count maxes out, it does
//    not roll over.
//
// 3) Add the two counts together.
//
// 4) If the sum is less than div, then the clock is too slow, so
//    decrease the trim code.  If the sum is greater than div, the
//    clock is too fast, so increase the trim code.  If the sum
//    is equal to div, the the trim code does not change.
//

module pll_controller(reset, clock, osc, div, trim);
    input reset;
    input clock;
    input osc;
    input [4:0] div;
    output [25:0] trim;		// Use ring_osc2x13, with 26 trim bits

    wire [25:0] trim;
    reg [2:0] oscbuf;
    reg [2:0] prep;

    reg [4:0] count0;
    reg [4:0] count1;
    reg [6:0] tval;	// Includes 2 bits fractional
    wire [4:0] tint;	// Integer part of the above

    wire [5:0] sum;

    assign sum = count0 + count1;
 
    // Integer to thermometer code (maybe there's an algorithmic way?)
    assign tint = tval[6:2];
                                     // |<--second-->|<-- first-->|
    assign trim = (tint == 5'd0)  ? 26'b0000000000000_0000000000000 :
          (tint == 5'd1)  ? 26'b0000000000000_0000000000001 :
          (tint == 5'd2)  ? 26'b0000000000000_0000001000001 :
          (tint == 5'd3)  ? 26'b0000000000000_0010001000001 :
          (tint == 5'd4)  ? 26'b0000000000000_0010001001001 :
          (tint == 5'd5)  ? 26'b0000000000000_0010101001001 :
          (tint == 5'd6)  ? 26'b0000000000000_1010101001001 :
          (tint == 5'd7)  ? 26'b0000000000000_1010101101001 :
          (tint == 5'd8)  ? 26'b0000000000000_1010101101101 :
          (tint == 5'd9)  ? 26'b0000000000000_1011101101101 :
          (tint == 5'd10) ? 26'b0000000000000_1011101111101 :
          (tint == 5'd11) ? 26'b0000000000000_1111101111101 :
          (tint == 5'd12) ? 26'b0000000000000_1111101111111 :
          (tint == 5'd13) ? 26'b0000000000000_1111111111111 :
          (tint == 5'd14) ? 26'b0000000000001_1111111111111 :
          (tint == 5'd15) ? 26'b0000001000001_1111111111111 :
          (tint == 5'd16) ? 26'b0010001000001_1111111111111 :
          (tint == 5'd17) ? 26'b0010001001001_1111111111111 :
          (tint == 5'd18) ? 26'b0010101001001_1111111111111 :
          (tint == 5'd19) ? 26'b1010101001001_1111111111111 :
          (tint == 5'd20) ? 26'b1010101101001_1111111111111 :
          (tint == 5'd21) ? 26'b1010101101101_1111111111111 :
          (tint == 5'd22) ? 26'b1011101101101_1111111111111 :
          (tint == 5'd23) ? 26'b1011101111101_1111111111111 :
          (tint == 5'd24) ? 26'b1111101111101_1111111111111 :
          (tint == 5'd25) ? 26'b1111101111111_1111111111111 :
                    26'b1111111111111_1111111111111;
   
    always @(posedge clock or posedge reset) begin
    if (reset == 1'b1) begin
        tval <= 7'd0;	// Note:  trim[0] must be zero for startup to work.
        oscbuf <= 3'd0;
        prep <= 3'd0;
        count0 <= 5'd0;
        count1 <= 5'd0;

    end else begin
        oscbuf <= {oscbuf[1:0], osc};

        if (oscbuf[2] != oscbuf[1]) begin
        count1 <= count0;
        count0 <= 5'b00001;
        prep <= {prep[1:0], 1'b1};

        if (prep == 3'b111) begin
            if (sum > div) begin
		if (tval < 127) begin
            	    tval <= tval + 1;
		end
            end else if (sum < div) begin
		if (tval > 0) begin
            	    tval <= tval - 1;
		end
            end
        end
        end else begin
        if (count0 != 5'b11111) begin
                count0 <= count0 + 1;
        end
        end
    end
    end

endmodule	// digital_pll_controller
`default_nettype wire

tb/tb_pll_controller_tval.v
`timescale 1ns/1ps

module tb_digital_pll_controller;
    reg reset;
    reg clock;
    reg osc;
    reg [4:0] div;

    wire [25:0] trim;

    pll_controller uut (
        .reset(reset),
        .clock(clock),
        .osc(osc),
        .div(div),
        .trim(trim)
    );

    initial begin
        $dumpfile("tb_pll_controller_tval.vcd");
        $dumpvars(0, tb_digital_pll_controller);
        
        reset = 1'b1;
        clock = 1'b0;
        osc   = 1'b0;
        div   = 5'd8; 
        #20;
        reset = 1'b0;
        
        #100;

        repeat(10) begin
        //random tu 1 den 31
            div = 1+{$random}%30; 
            
            $display("------------------------------------");
            $display("div = %d", div);

            #500;
            
            // setting div gap 8 lan osc nen kiem tra dieu kien voi 8
            if (div < 8) begin // clock nhanh hon mong muon->tang tval-> tang delay->giam clock
                if (uut.tval > 0) begin
                    $display("PASS: div = %d, tval = %d.", div, uut.tval);
                end else begin
                    $display("FAIL: div = %d, tval = %d.", div, uut.tval);
                end
            end else if (div > 8) begin //clock cham hon -> giam tval -> giam delay-> giam clock
                if (uut.tval == 0) begin
                    $display("PASS: div = %d, tval = %d bang 0.", div, uut.tval);
                end else begin
                    $display("FAIL: div = %d, tval = %d. khac 0", div, uut.tval);
                end
            end else begin // div == 8
                if (uut.tval == 0) begin
                     $display("PASS: div = 8, gia tri mac dinh.");
                end else begin
                    $display("FAIL: div = 8, tval = %d khong bang 0.", uut.tval);
                end
            end
        end
        
        #100;
        $finish;//end
    end

    always #5 clock = ~clock;
    always #40 osc = ~osc;

endmodule

waves/waves_pll_controller_tval.vcd
$date
	Mon Jul  7 16:23:42 2025
$end
$version
	Icarus Verilog
$end
$timescale
	1ps
$end
$scope module tb_digital_pll_controller $end
$var wire 26 ! trim [25:0] $end
$var reg 1 " clock $end
$var reg 5 # div [4:0] $end
$var reg 1 $ osc $end
$var reg 1 % reset $end
$scope module uut $end
$var wire 1 " clock $end
$var wire 5 & div [4:0] $end
$var wire 1 $ osc $end
$var wire 1 % reset $end
$var wire 26 ' trim [25:0] $end
$var wire 5 ( tint [4:0] $end
$var wire 6 ) sum [5:0] $end
$var reg 5 * count0 [4:0] $end
$var reg 5 + count1 [4:0] $end
$var reg 3 , oscbuf [2:0] $end
$var reg 3 - prep [2:0] $end
$var reg 7 . tval [6:0] $end
$upscope $end
$upscope $end
$enddefinitions $end
#0
$dumpvars
b0 .
b0 -
b0 ,
b0 +
b0 *
b0 )
b0 (
b0 '
b1000 &
1%
0$
b1000 #
0"
b0 !
$end
#5000
1"
#10000
0"
#15000
1"
#20000
0"
0%
#25000
b1 )
b1 *
1"
#30000
0"
#35000
b10 )
b10 *
1"
#40000
0"
1$
#45000
b11 )
b11 *
b1 ,
1"
#50000
0"
#55000
b100 )
b100 *
b11 ,
1"
#60000
0"
#65000
b1 -
b1 *
b101 )
b100 +
b111 ,
1"
#70000
0"
#75000
b110 )
b10 *
1"
#80000
0"
0$
#85000
b111 )
b11 *
b110 ,
1"
#90000
0"
#95000
b1000 )
b100 *
b100 ,
1"
#100000
0"
#105000
b11 -
b101 )
b1 *
b0 ,
1"
#110000
0"
#115000
b110 )
b10 *
1"
#120000
0"
1$
b1001 #
b1001 &
#125000
b111 )
b11 *
b1 ,
1"
#130000
0"
#135000
b1000 )
b100 *
b11 ,
1"
#140000
0"
#145000
b111 -
b101 )
b1 *
b111 ,
1"
#150000
0"
#155000
b110 )
b10 *
1"
#160000
0"
0$
#165000
b111 )
b11 *
b110 ,
1"
#170000
0"
#175000
b1000 )
b100 *
b100 ,
1"
#180000
0"
#185000
b101 )
b1 *
b0 ,
1"
#190000
0"
#195000
b110 )
b10 *
1"
#200000
0"
1$
#205000
b111 )
b11 *
b1 ,
1"
#210000
0"
#215000
b1000 )
b100 *
b11 ,
1"
#220000
0"
#225000
b101 )
b1 *
b111 ,
1"
#230000
0"
#235000
b110 )
b10 *
1"
#240000
0"
0$
#245000
b111 )
b11 *
b110 ,
1"
#250000
0"
#255000
b1000 )
b100 *
b100 ,
1"
#260000
0"
#265000
b101 )
b1 *
b0 ,
1"
#270000
0"
#275000
b110 )
b10 *
1"
#280000
0"
1$
#285000
b111 )
b11 *
b1 ,
1"
#290000
0"
#295000
b1000 )
b100 *
b11 ,
1"
#300000
0"
#305000
b101 )
b1 *
b111 ,
1"
#310000
0"
#315000
b110 )
b10 *
1"
#320000
0"
0$
#325000
b111 )
b11 *
b110 ,
1"
#330000
0"
#335000
b1000 )
b100 *
b100 ,
1"
#340000
0"
#345000
b101 )
b1 *
b0 ,
1"
#350000
0"
#355000
b110 )
b10 *
1"
#360000
0"
1$
#365000
b111 )
b11 *
b1 ,
1"
#370000
0"
#375000
b1000 )
b100 *
b11 ,
1"
#380000
0"
#385000
b101 )
b1 *
b111 ,
1"
#390000
0"
#395000
b110 )
b10 *
1"
#400000
0"
0$
#405000
b111 )
b11 *
b110 ,
1"
#410000
0"
#415000
b1000 )
b100 *
b100 ,
1"
#420000
0"
#425000
b101 )
b1 *
b0 ,
1"
#430000
0"
#435000
b110 )
b10 *
1"
#440000
0"
1$
#445000
b111 )
b11 *
b1 ,
1"
#450000
0"
#455000
b1000 )
b100 *
b11 ,
1"
#460000
0"
#465000
b101 )
b1 *
b111 ,
1"
#470000
0"
#475000
b110 )
b10 *
1"
#480000
0"
0$
#485000
b111 )
b11 *
b110 ,
1"
#490000
0"
#495000
b1000 )
b100 *
b100 ,
1"
#500000
0"
#505000
b101 )
b1 *
b0 ,
1"
#510000
0"
#515000
b110 )
b10 *
1"
#520000
0"
1$
#525000
b111 )
b11 *
b1 ,
1"
#530000
0"
#535000
b1000 )
b100 *
b11 ,
1"
#540000
0"
#545000
b101 )
b1 *
b111 ,
1"
#550000
0"
#555000
b110 )
b10 *
1"
#560000
0"
0$
#565000
b111 )
b11 *
b110 ,
1"
#570000
0"
#575000
b1000 )
b100 *
b100 ,
1"
#580000
0"
#585000
b101 )
b1 *
b0 ,
1"
#590000
0"
#595000
b110 )
b10 *
1"
#600000
0"
1$
#605000
b111 )
b11 *
b1 ,
1"
#610000
0"
#615000
b1000 )
b100 *
b11 ,
1"
#620000
0"
b11100 #
b11100 &
#625000
b101 )
b1 *
b111 ,
1"
#630000
0"
#635000
b110 )
b10 *
1"
#640000
0"
0$
#645000
b111 )
b11 *
b110 ,
1"
#650000
0"
#655000
b1000 )
b100 *
b100 ,
1"
#660000
0"
#665000
b101 )
b1 *
b0 ,
1"
#670000
0"
#675000
b110 )
b10 *
1"
#680000
0"
1$
#685000
b111 )
b11 *
b1 ,
1"
#690000
0"
#695000
b1000 )
b100 *
b11 ,
1"
#700000
0"
#705000
b101 )
b1 *
b111 ,
1"
#710000
0"
#715000
b110 )
b10 *
1"
#720000
0"
0$
#725000
b111 )
b11 *
b110 ,
1"
#730000
0"
#735000
b1000 )
b100 *
b100 ,
1"
#740000
0"
#745000
b101 )
b1 *
b0 ,
1"
#750000
0"
#755000
b110 )
b10 *
1"
#760000
0"
1$
#765000
b111 )
b11 *
b1 ,
1"
#770000
0"
#775000
b1000 )
b100 *
b11 ,
1"
#780000
0"
#785000
b101 )
b1 *
b111 ,
1"
#790000
0"
#795000
b110 )
b10 *
1"
#800000
0"
0$
#805000
b111 )
b11 *
b110 ,
1"
#810000
0"
#815000
b1000 )
b100 *
b100 ,
1"
#820000
0"
#825000
b101 )
b1 *
b0 ,
1"
#830000
0"
#835000
b110 )
b10 *
1"
#840000
0"
1$
#845000
b111 )
b11 *
b1 ,
1"
#850000
0"
#855000
b1000 )
b100 *
b11 ,
1"
#860000
0"
#865000
b101 )
b1 *
b111 ,
1"
#870000
0"
#875000
b110 )
b10 *
1"
#880000
0"
0$
#885000
b111 )
b11 *
b110 ,
1"
#890000
0"
#895000
b1000 )
b100 *
b100 ,
1"
#900000
0"
#905000
b101 )
b1 *
b0 ,
1"
#910000
0"
#915000
b110 )
b10 *
1"
#920000
0"
1$
#925000
b111 )
b11 *
b1 ,
1"
#930000
0"
#935000
b1000 )
b100 *
b11 ,
1"
#940000
0"
#945000
b101 )
b1 *
b111 ,
1"
#950000
0"
#955000
b110 )
b10 *
1"
#960000
0"
0$
#965000
b111 )
b11 *
b110 ,
1"
#970000
0"
#975000
b1000 )
b100 *
b100 ,
1"
#980000
0"
#985000
b101 )
b1 *
b0 ,
1"
#990000
0"
#995000
b110 )
b10 *
1"
#1000000
0"
1$
#1005000
b111 )
b11 *
b1 ,
1"
#1010000
0"
#1015000
b1000 )
b100 *
b11 ,
1"
#1020000
0"
#1025000
b101 )
b1 *
b111 ,
1"
#1030000
0"
#1035000
b110 )
b10 *
1"
#1040000
0"
0$
#1045000
b111 )
b11 *
b110 ,
1"
#1050000
0"
#1055000
b1000 )
b100 *
b100 ,
1"
#1060000
0"
#1065000
b101 )
b1 *
b0 ,
1"
#1070000
0"
#1075000
b110 )
b10 *
1"
#1080000
0"
1$
#1085000
b111 )
b11 *
b1 ,
1"
#1090000
0"
#1095000
b1000 )
b100 *
b11 ,
1"
#1100000
0"
#1105000
b101 )
b1 *
b111 ,
1"
#1110000
0"
#1115000
b110 )
b10 *
1"
#1120000
0"
0$
b1000 #
b1000 &
#1125000
b111 )
b11 *
b110 ,
1"
#1130000
0"
#1135000
b1000 )
b100 *
b100 ,
1"
#1140000
0"
#1145000
b101 )
b1 *
b0 ,
1"
#1150000
0"
#1155000
b110 )
b10 *
1"
#1160000
0"
1$
#1165000
b111 )
b11 *
b1 ,
1"
#1170000
0"
#1175000
b1000 )
b100 *
b11 ,
1"
#1180000
0"
#1185000
b101 )
b1 *
b111 ,
1"
#1190000
0"
#1195000
b110 )
b10 *
1"
#1200000
0"
0$
#1205000
b111 )
b11 *
b110 ,
1"
#1210000
0"
#1215000
b1000 )
b100 *
b100 ,
1"
#1220000
0"
#1225000
b101 )
b1 *
b0 ,
1"
#1230000
0"
#1235000
b110 )
b10 *
1"
#1240000
0"
1$
#1245000
b111 )
b11 *
b1 ,
1"
#1250000
0"
#1255000
b1000 )
b100 *
b11 ,
1"
#1260000
0"
#1265000
b101 )
b1 *
b111 ,
1"
#1270000
0"
#1275000
b110 )
b10 *
1"
#1280000
0"
0$
#1285000
b111 )
b11 *
b110 ,
1"
#1290000
0"
#1295000
b1000 )
b100 *
b100 ,
1"
#1300000
0"
#1305000
b101 )
b1 *
b0 ,
1"
#1310000
0"
#1315000
b110 )
b10 *
1"
#1320000
0"
1$
#1325000
b111 )
b11 *
b1 ,
1"
#1330000
0"
#1335000
b1000 )
b100 *
b11 ,
1"
#1340000
0"
#1345000
b101 )
b1 *
b111 ,
1"
#1350000
0"
#1355000
b110 )
b10 *
1"
#1360000
0"
0$
#1365000
b111 )
b11 *
b110 ,
1"
#1370000
0"
#1375000
b1000 )
b100 *
b100 ,
1"
#1380000
0"
#1385000
b101 )
b1 *
b0 ,
1"
#1390000
0"
#1395000
b110 )
b10 *
1"
#1400000
0"
1$
#1405000
b111 )
b11 *
b1 ,
1"
#1410000
0"
#1415000
b1000 )
b100 *
b11 ,
1"
#1420000
0"
#1425000
b101 )
b1 *
b111 ,
1"
#1430000
0"
#1435000
b110 )
b10 *
1"
#1440000
0"
0$
#1445000
b111 )
b11 *
b110 ,
1"
#1450000
0"
#1455000
b1000 )
b100 *
b100 ,
1"
#1460000
0"
#1465000
b101 )
b1 *
b0 ,
1"
#1470000
0"
#1475000
b110 )
b10 *
1"
#1480000
0"
1$
#1485000
b111 )
b11 *
b1 ,
1"
#1490000
0"
#1495000
b1000 )
b100 *
b11 ,
1"
#1500000
0"
#1505000
b101 )
b1 *
b111 ,
1"
#1510000
0"
#1515000
b110 )
b10 *
1"
#1520000
0"
0$
#1525000
b111 )
b11 *
b110 ,
1"
#1530000
0"
#1535000
b1000 )
b100 *
b100 ,
1"
#1540000
0"
#1545000
b101 )
b1 *
b0 ,
1"
#1550000
0"
#1555000
b110 )
b10 *
1"
#1560000
0"
1$
#1565000
b111 )
b11 *
b1 ,
1"
#1570000
0"
#1575000
b1000 )
b100 *
b11 ,
1"
#1580000
0"
#1585000
b101 )
b1 *
b111 ,
1"
#1590000
0"
#1595000
b110 )
b10 *
1"
#1600000
0"
0$
#1605000
b111 )
b11 *
b110 ,
1"
#1610000
0"
#1615000
b1000 )
b100 *
b100 ,
1"
#1620000
0"
b10010 #
b10010 &
#1625000
b101 )
b1 *
b0 ,
1"
#1630000
0"
#1635000
b110 )
b10 *
1"
#1640000
0"
1$
#1645000
b111 )
b11 *
b1 ,
1"
#1650000
0"
#1655000
b1000 )
b100 *
b11 ,
1"
#1660000
0"
#1665000
b101 )
b1 *
b111 ,
1"
#1670000
0"
#1675000
b110 )
b10 *
1"
#1680000
0"
0$
#1685000
b111 )
b11 *
b110 ,
1"
#1690000
0"
#1695000
b1000 )
b100 *
b100 ,
1"
#1700000
0"
#1705000
b101 )
b1 *
b0 ,
1"
#1710000
0"
#1715000
b110 )
b10 *
1"
#1720000
0"
1$
#1725000
b111 )
b11 *
b1 ,
1"
#1730000
0"
#1735000
b1000 )
b100 *
b11 ,
1"
#1740000
0"
#1745000
b101 )
b1 *
b111 ,
1"
#1750000
0"
#1755000
b110 )
b10 *
1"
#1760000
0"
0$
#1765000
b111 )
b11 *
b110 ,
1"
#1770000
0"
#1775000
b1000 )
b100 *
b100 ,
1"
#1780000
0"
#1785000
b101 )
b1 *
b0 ,
1"
#1790000
0"
#1795000
b110 )
b10 *
1"
#1800000
0"
1$
#1805000
b111 )
b11 *
b1 ,
1"
#1810000
0"
#1815000
b1000 )
b100 *
b11 ,
1"
#1820000
0"
#1825000
b101 )
b1 *
b111 ,
1"
#1830000
0"
#1835000
b110 )
b10 *
1"
#1840000
0"
0$
#1845000
b111 )
b11 *
b110 ,
1"
#1850000
0"
#1855000
b1000 )
b100 *
b100 ,
1"
#1860000
0"
#1865000
b101 )
b1 *
b0 ,
1"
#1870000
0"
#1875000
b110 )
b10 *
1"
#1880000
0"
1$
#1885000
b111 )
b11 *
b1 ,
1"
#1890000
0"
#1895000
b1000 )
b100 *
b11 ,
1"
#1900000
0"
#1905000
b101 )
b1 *
b111 ,
1"
#1910000
0"
#1915000
b110 )
b10 *
1"
#1920000
0"
0$
#1925000
b111 )
b11 *
b110 ,
1"
#1930000
0"
#1935000
b1000 )
b100 *
b100 ,
1"
#1940000
0"
#1945000
b101 )
b1 *
b0 ,
1"
#1950000
0"
#1955000
b110 )
b10 *
1"
#1960000
0"
1$
#1965000
b111 )
b11 *
b1 ,
1"
#1970000
0"
#1975000
b1000 )
b100 *
b11 ,
1"
#1980000
0"
#1985000
b101 )
b1 *
b111 ,
1"
#1990000
0"
#1995000
b110 )
b10 *
1"
#2000000
0"
0$
#2005000
b111 )
b11 *
b110 ,
1"
#2010000
0"
#2015000
b1000 )
b100 *
b100 ,
1"
#2020000
0"
#2025000
b101 )
b1 *
b0 ,
1"
#2030000
0"
#2035000
b110 )
b10 *
1"
#2040000
0"
1$
#2045000
b111 )
b11 *
b1 ,
1"
#2050000
0"
#2055000
b1000 )
b100 *
b11 ,
1"
#2060000
0"
#2065000
b101 )
b1 *
b111 ,
1"
#2070000
0"
#2075000
b110 )
b10 *
1"
#2080000
0"
0$
#2085000
b111 )
b11 *
b110 ,
1"
#2090000
0"
#2095000
b1000 )
b100 *
b100 ,
1"
#2100000
0"
#2105000
b101 )
b1 *
b0 ,
1"
#2110000
0"
#2115000
b110 )
b10 *
1"
#2120000
0"
1$
b11100 #
b11100 &
#2125000
b111 )
b11 *
b1 ,
1"
#2130000
0"
#2135000
b1000 )
b100 *
b11 ,
1"
#2140000
0"
#2145000
b101 )
b1 *
b111 ,
1"
#2150000
0"
#2155000
b110 )
b10 *
1"
#2160000
0"
0$
#2165000
b111 )
b11 *
b110 ,
1"
#2170000
0"
#2175000
b1000 )
b100 *
b100 ,
1"
#2180000
0"
#2185000
b101 )
b1 *
b0 ,
1"
#2190000
0"
#2195000
b110 )
b10 *
1"
#2200000
0"
1$
#2205000
b111 )
b11 *
b1 ,
1"
#2210000
0"
#2215000
b1000 )
b100 *
b11 ,
1"
#2220000
0"
#2225000
b101 )
b1 *
b111 ,
1"
#2230000
0"
#2235000
b110 )
b10 *
1"
#2240000
0"
0$
#2245000
b111 )
b11 *
b110 ,
1"
#2250000
0"
#2255000
b1000 )
b100 *
b100 ,
1"
#2260000
0"
#2265000
b101 )
b1 *
b0 ,
1"
#2270000
0"
#2275000
b110 )
b10 *
1"
#2280000
0"
1$
#2285000
b111 )
b11 *
b1 ,
1"
#2290000
0"
#2295000
b1000 )
b100 *
b11 ,
1"
#2300000
0"
#2305000
b101 )
b1 *
b111 ,
1"
#2310000
0"
#2315000
b110 )
b10 *
1"
#2320000
0"
0$
#2325000
b111 )
b11 *
b110 ,
1"
#2330000
0"
#2335000
b1000 )
b100 *
b100 ,
1"
#2340000
0"
#2345000
b101 )
b1 *
b0 ,
1"
#2350000
0"
#2355000
b110 )
b10 *
1"
#2360000
0"
1$
#2365000
b111 )
b11 *
b1 ,
1"
#2370000
0"
#2375000
b1000 )
b100 *
b11 ,
1"
#2380000
0"
#2385000
b101 )
b1 *
b111 ,
1"
#2390000
0"
#2395000
b110 )
b10 *
1"
#2400000
0"
0$
#2405000
b111 )
b11 *
b110 ,
1"
#2410000
0"
#2415000
b1000 )
b100 *
b100 ,
1"
#2420000
0"
#2425000
b101 )
b1 *
b0 ,
1"
#2430000
0"
#2435000
b110 )
b10 *
1"
#2440000
0"
1$
#2445000
b111 )
b11 *
b1 ,
1"
#2450000
0"
#2455000
b1000 )
b100 *
b11 ,
1"
#2460000
0"
#2465000
b101 )
b1 *
b111 ,
1"
#2470000
0"
#2475000
b110 )
b10 *
1"
#2480000
0"
0$
#2485000
b111 )
b11 *
b110 ,
1"
#2490000
0"
#2495000
b1000 )
b100 *
b100 ,
1"
#2500000
0"
#2505000
b101 )
b1 *
b0 ,
1"
#2510000
0"
#2515000
b110 )
b10 *
1"
#2520000
0"
1$
#2525000
b111 )
b11 *
b1 ,
1"
#2530000
0"
#2535000
b1000 )
b100 *
b11 ,
1"
#2540000
0"
#2545000
b101 )
b1 *
b111 ,
1"
#2550000
0"
#2555000
b110 )
b10 *
1"
#2560000
0"
0$
#2565000
b111 )
b11 *
b110 ,
1"
#2570000
0"
#2575000
b1000 )
b100 *
b100 ,
1"
#2580000
0"
#2585000
b101 )
b1 *
b0 ,
1"
#2590000
0"
#2595000
b110 )
b10 *
1"
#2600000
0"
1$
#2605000
b111 )
b11 *
b1 ,
1"
#2610000
0"
#2615000
b1000 )
b100 *
b11 ,
1"
#2620000
0"
b10010 #
b10010 &
#2625000
b101 )
b1 *
b111 ,
1"
#2630000
0"
#2635000
b110 )
b10 *
1"
#2640000
0"
0$
#2645000
b111 )
b11 *
b110 ,
1"
#2650000
0"
#2655000
b1000 )
b100 *
b100 ,
1"
#2660000
0"
#2665000
b101 )
b1 *
b0 ,
1"
#2670000
0"
#2675000
b110 )
b10 *
1"
#2680000
0"
1$
#2685000
b111 )
b11 *
b1 ,
1"
#2690000
0"
#2695000
b1000 )
b100 *
b11 ,
1"
#2700000
0"
#2705000
b101 )
b1 *
b111 ,
1"
#2710000
0"
#2715000
b110 )
b10 *
1"
#2720000
0"
0$
#2725000
b111 )
b11 *
b110 ,
1"
#2730000
0"
#2735000
b1000 )
b100 *
b100 ,
1"
#2740000
0"
#2745000
b101 )
b1 *
b0 ,
1"
#2750000
0"
#2755000
b110 )
b10 *
1"
#2760000
0"
1$
#2765000
b111 )
b11 *
b1 ,
1"
#2770000
0"
#2775000
b1000 )
b100 *
b11 ,
1"
#2780000
0"
#2785000
b101 )
b1 *
b111 ,
1"
#2790000
0"
#2795000
b110 )
b10 *
1"
#2800000
0"
0$
#2805000
b111 )
b11 *
b110 ,
1"
#2810000
0"
#2815000
b1000 )
b100 *
b100 ,
1"
#2820000
0"
#2825000
b101 )
b1 *
b0 ,
1"
#2830000
0"
#2835000
b110 )
b10 *
1"
#2840000
0"
1$
#2845000
b111 )
b11 *
b1 ,
1"
#2850000
0"
#2855000
b1000 )
b100 *
b11 ,
1"
#2860000
0"
#2865000
b101 )
b1 *
b111 ,
1"
#2870000
0"
#2875000
b110 )
b10 *
1"
#2880000
0"
0$
#2885000
b111 )
b11 *
b110 ,
1"
#2890000
0"
#2895000
b1000 )
b100 *
b100 ,
1"
#2900000
0"
#2905000
b101 )
b1 *
b0 ,
1"
#2910000
0"
#2915000
b110 )
b10 *
1"
#2920000
0"
1$
#2925000
b111 )
b11 *
b1 ,
1"
#2930000
0"
#2935000
b1000 )
b100 *
b11 ,
1"
#2940000
0"
#2945000
b101 )
b1 *
b111 ,
1"
#2950000
0"
#2955000
b110 )
b10 *
1"
#2960000
0"
0$
#2965000
b111 )
b11 *
b110 ,
1"
#2970000
0"
#2975000
b1000 )
b100 *
b100 ,
1"
#2980000
0"
#2985000
b101 )
b1 *
b0 ,
1"
#2990000
0"
#2995000
b110 )
b10 *
1"
#3000000
0"
1$
#3005000
b111 )
b11 *
b1 ,
1"
#3010000
0"
#3015000
b1000 )
b100 *
b11 ,
1"
#3020000
0"
#3025000
b101 )
b1 *
b111 ,
1"
#3030000
0"
#3035000
b110 )
b10 *
1"
#3040000
0"
0$
#3045000
b111 )
b11 *
b110 ,
1"
#3050000
0"
#3055000
b1000 )
b100 *
b100 ,
1"
#3060000
0"
#3065000
b101 )
b1 *
b0 ,
1"
#3070000
0"
#3075000
b110 )
b10 *
1"
#3080000
0"
1$
#3085000
b111 )
b11 *
b1 ,
1"
#3090000
0"
#3095000
b1000 )
b100 *
b11 ,
1"
#3100000
0"
#3105000
b101 )
b1 *
b111 ,
1"
#3110000
0"
#3115000
b110 )
b10 *
1"
#3120000
0"
0$
b110 #
b110 &
#3125000
b111 )
b11 *
b110 ,
1"
#3130000
0"
#3135000
b1000 )
b100 *
b100 ,
1"
#3140000
0"
#3145000
b1 .
b101 )
b1 *
b0 ,
1"
#3150000
0"
#3155000
b110 )
b10 *
1"
#3160000
0"
1$
#3165000
b111 )
b11 *
b1 ,
1"
#3170000
0"
#3175000
b1000 )
b100 *
b11 ,
1"
#3180000
0"
#3185000
b10 .
b101 )
b1 *
b111 ,
1"
#3190000
0"
#3195000
b110 )
b10 *
1"
#3200000
0"
0$
#3205000
b111 )
b11 *
b110 ,
1"
#3210000
0"
#3215000
b1000 )
b100 *
b100 ,
1"
#3220000
0"
#3225000
b11 .
b101 )
b1 *
b0 ,
1"
#3230000
0"
#3235000
b110 )
b10 *
1"
#3240000
0"
1$
#3245000
b111 )
b11 *
b1 ,
1"
#3250000
0"
#3255000
b1000 )
b100 *
b11 ,
1"
#3260000
0"
#3265000
b1 !
b1 '
b1 (
b100 .
b101 )
b1 *
b111 ,
1"
#3270000
0"
#3275000
b110 )
b10 *
1"
#3280000
0"
0$
#3285000
b111 )
b11 *
b110 ,
1"
#3290000
0"
#3295000
b1000 )
b100 *
b100 ,
1"
#3300000
0"
#3305000
b101 .
b101 )
b1 *
b0 ,
1"
#3310000
0"
#3315000
b110 )
b10 *
1"
#3320000
0"
1$
#3325000
b111 )
b11 *
b1 ,
1"
#3330000
0"
#3335000
b1000 )
b100 *
b11 ,
1"
#3340000
0"
#3345000
b110 .
b101 )
b1 *
b111 ,
1"
#3350000
0"
#3355000
b110 )
b10 *
1"
#3360000
0"
0$
#3365000
b111 )
b11 *
b110 ,
1"
#3370000
0"
#3375000
b1000 )
b100 *
b100 ,
1"
#3380000
0"
#3385000
b111 .
b101 )
b1 *
b0 ,
1"
#3390000
0"
#3395000
b110 )
b10 *
1"
#3400000
0"
1$
#3405000
b111 )
b11 *
b1 ,
1"
#3410000
0"
#3415000
b1000 )
b100 *
b11 ,
1"
#3420000
0"
#3425000
b1000001 !
b1000001 '
b10 (
b1000 .
b101 )
b1 *
b111 ,
1"
#3430000
0"
#3435000
b110 )
b10 *
1"
#3440000
0"
0$
#3445000
b111 )
b11 *
b110 ,
1"
#3450000
0"
#3455000
b1000 )
b100 *
b100 ,
1"
#3460000
0"
#3465000
b1001 .
b101 )
b1 *
b0 ,
1"
#3470000
0"
#3475000
b110 )
b10 *
1"
#3480000
0"
1$
#3485000
b111 )
b11 *
b1 ,
1"
#3490000
0"
#3495000
b1000 )
b100 *
b11 ,
1"
#3500000
0"
#3505000
b1010 .
b101 )
b1 *
b111 ,
1"
#3510000
0"
#3515000
b110 )
b10 *
1"
#3520000
0"
0$
#3525000
b111 )
b11 *
b110 ,
1"
#3530000
0"
#3535000
b1000 )
b100 *
b100 ,
1"
#3540000
0"
#3545000
b1011 .
b101 )
b1 *
b0 ,
1"
#3550000
0"
#3555000
b110 )
b10 *
1"
#3560000
0"
1$
#3565000
b111 )
b11 *
b1 ,
1"
#3570000
0"
#3575000
b1000 )
b100 *
b11 ,
1"
#3580000
0"
#3585000
b10001000001 !
b10001000001 '
b11 (
b1100 .
b101 )
b1 *
b111 ,
1"
#3590000
0"
#3595000
b110 )
b10 *
1"
#3600000
0"
0$
#3605000
b111 )
b11 *
b110 ,
1"
#3610000
0"
#3615000
b1000 )
b100 *
b100 ,
1"
#3620000
0"
b10111 #
b10111 &
#3625000
b1000001 !
b1000001 '
b10 (
b1011 .
b101 )
b1 *
b0 ,
1"
#3630000
0"
#3635000
b110 )
b10 *
1"
#3640000
0"
1$
#3645000
b111 )
b11 *
b1 ,
1"
#3650000
0"
